README.md
setup.cfg
setup.py
f_encrypt.egg-info/PKG-INFO
f_encrypt.egg-info/SOURCES.txt
f_encrypt.egg-info/dependency_links.txt
f_encrypt.egg-info/entry_points.txt
f_encrypt.egg-info/requires.txt
f_encrypt.egg-info/top_level.txt
fencrypt/__init__.py
fencrypt/aes.py
fencrypt/entrypoint.py
fencrypt/lib.py