Metadata-Version: 2.1
Name: f-encrypt
Version: 1.1
Summary: UNKNOWN
Home-page: https://github.com/kylep/f-encrypt
Author: Kyle Pericak
Author-email: kyle@pericak.com
License: UNKNOWN
Download-URL: https://github.com/kylep/f-encrypt/archive/1.01.tar.gz
Platform: UNKNOWN
Classifier: Topic :: Security :: Cryptography
